<?xml version="1.0" encoding="UTF-8"?>
<!--
This is free and unencumbered software released into the public domain.
For specific language governing permissions and limitations refer to
the LICENSE.md file or http://unlicense.org
-->
<screen xmlns:xsi="http://www.w3.org/2001/XMLSchema-instance" xsi:noNamespaceSchemaLocation="http://moqui.org/xsd/xml-screen-1.5.xsd"
        default-menu-title="Supplier" default-menu-index="1">

    <parameter name="partyId" required="true"/>

    <transition name="findOrder"><default-response url="."/></transition><!-- TODO ../../Order/FindOrder -->
    <transition name="updateParty"><service-call name="mantle.party.PartyServices.update#PartyDetail"/>
        <default-response url="."/></transition>

    <transition name="createPartyRole"><service-call name="create#mantle.party.PartyRole"/>
        <default-response url="."/></transition>
    <transition name="deletePartyRole"><service-call name="delete#mantle.party.PartyRole"/>
        <default-response url="."/></transition>

    <transition name="createPartyIdentification"><service-call name="create#mantle.party.PartyIdentification"/>
        <default-response url="."/></transition>
    <transition name="updatePartyIdentification"><service-call name="update#mantle.party.PartyIdentification"/>
        <default-response url="."/></transition>
    <transition name="deletePartyIdentification"><parameter name="partyIdTypeEnumId"/>
        <service-call name="delete#mantle.party.PartyIdentification"/><default-response url="."/></transition>

    <transition name="updateContactInfo"><default-response url="UpdateContactInfo"/></transition>
    <transition name="removeContactInfo"><service-call name="mantle.party.ContactServices.delete#PartyContactMech"/>
        <default-response url="."/></transition>

    <transition name="createPartyNote"><service-call name="create#mantle.party.PartyNote"/>
        <default-response url="."/></transition>
    <transition name="updatePartyNote"><service-call name="update#mantle.party.PartyNote"/>
        <default-response url="."/></transition>

    <subscreens><subscreens-item name="UpdateContactInfo"
            location="component://PopCommerce/screen/PopCommerceAdmin/Customer/EditCustomer/UpdateContactInfo.xml"/></subscreens>

    <actions>
        <entity-find-one entity-name="mantle.party.PartyDetail" value-field="party"/>
    </actions>
    <widgets>
        <container-row>
            <row-col lg="6">
                <link url="findOrder" text="Orders" parameter-map="[vendorPartyId:partyId]"/>

                <section-include name="EditPartySection" location="component://PopCommerce/screen/PopCommerceAdmin/Customer/EditCustomer.xml"/>
                <section-include name="RolesSection" location="component://PopCommerce/screen/PopCommerceAdmin/Customer/EditCustomer.xml"/>
                <section-include name="PartyIdentificationSection" location="component://PopCommerce/screen/PopCommerceAdmin/Customer/EditCustomer.xml"/>
            </row-col>
            <row-col lg="6">
                <section-include name="ContactInfoSection" location="component://PopCommerce/screen/PopCommerceAdmin/Customer/EditCustomer.xml"/>
                <section-include name="NotesSection" location="component://PopCommerce/screen/PopCommerceAdmin/Customer/EditCustomer.xml"/>
            </row-col>
        </container-row>
    </widgets>
</screen>
